<?xml version="1.1" encoding="UTF-8" standalone="no"?>
<databaseChangeLog xmlns="http://www.liquibase.org/xml/ns/dbchangelog" xmlns:ext="http://www.liquibase.org/xml/ns/dbchangelog-ext" xmlns:xsi="http://www.w3.org/2001/XMLSchema-instance" xsi:schemaLocation="http://www.liquibase.org/xml/ns/dbchangelog-ext http://www.liquibase.org/xml/ns/dbchangelog/dbchangelog-ext.xsd http://www.liquibase.org/xml/ns/dbchangelog http://www.liquibase.org/xml/ns/dbchangelog/dbchangelog-3.6.xsd" logicalFilePath="ep_00066.xml">
    <changeSet author="European Dynamics" id="1560757444927-4">
        <addColumn tableName="mqtt_server">
            <column name="topic_ping" type="VARCHAR(255 BYTE)">
                <constraints nullable="false"/>
            </column>
        </addColumn>
    </changeSet>
    <changeSet author="European Dynamics" id="1560757444927-1">
        <addNotNullConstraint columnDataType="varchar(255)" columnName="topic_control" tableName="mqtt_server"/>
    </changeSet>
    <changeSet author="European Dynamics" id="1560757444927-2">
        <addNotNullConstraint columnDataType="varchar(255)" columnName="topic_metadata" tableName="mqtt_server"/>
    </changeSet>
    <changeSet author="European Dynamics" id="1560757444927-3">
        <addNotNullConstraint columnDataType="varchar(255)" columnName="topic_telemetry" tableName="mqtt_server"/>
    </changeSet>
</databaseChangeLog>
